crovia_cep-0.1.0.dist-info/licenses/LICENSE
croviacep/__init__.py
croviacep/cli.py
crovia_cep-0.1.0.dist-info/METADATA
crovia_cep-0.1.0.dist-info/WHEEL
crovia_cep-0.1.0.dist-info/entry_points.txt
crovia_cep-0.1.0.dist-info/top_level.txt
crovia_cep-0.1.0.dist-info/RECORD
