Metadata-Version: 2.4
Name: crovia-cep
Version: 0.1.0
Summary: CEP Capsule Verifier for CROVIA evidence blocks
Author-email: Crovia Trust <info@croviatrust.com>
License: Apache License 2.0
Project-URL: Homepage, https://huggingface.co/datasets/Crovia/cep-capsules
Project-URL: Source, https://github.com/croviatrust/crovia-cep
Requires-Python: >=3.8
License-File: LICENSE
Requires-Dist: requests>=2.31.0
Requires-Dist: huggingface-hub>=0.23.0
Dynamic: license-file
